AISTLAB_novel_downloader-1.0.0.dist-info/DESCRIPTION.rst
AISTLAB_novel_downloader-1.0.0.dist-info/METADATA
AISTLAB_novel_downloader-1.0.0.dist-info/RECORD
AISTLAB_novel_downloader-1.0.0.dist-info/WHEEL
AISTLAB_novel_downloader-1.0.0.dist-info/entry_points.txt
AISTLAB_novel_downloader-1.0.0.dist-info/metadata.json
AISTLAB_novel_downloader-1.0.0.dist-info/top_level.txt
novel_downloader/__init__.py
novel_downloader/web.py
