Metadata-Version: 2.0
Name: AISTLAB-novel-downloader
Version: 1.0.0
Summary: novel downloader online service
Home-page: https://github.com/winxos/novel_downloader
Author: winxos
Author-email: winxos@hotmail.com
License: MIT License
Platform: UNKNOWN
Classifier: Development Status :: 3 - Alpha
Classifier: Intended Audience :: End Users/Desktop
Classifier: Topic :: Utilities
Classifier: Programming Language :: Python :: 3
Classifier: Programming Language :: Python :: 3.2
Classifier: Programming Language :: Python :: 3.3
Classifier: Programming Language :: Python :: 3.4
Classifier: Programming Language :: Python :: 3.5
Classifier: Programming Language :: Python :: 3.6
Requires-Dist: aistlab-novel-grab
